Workbook

Sheet BBDD
A1: BASE DE DATOS COMERCIAL - GRIFF SALUD
A2: FECHA CONTACTO | B2: MES | C2: NOMBRE | D2: TELEFONO | E2: CANAL | F2: COMERCIAL | G2: LUGAR | H2: ESTADO | I2: PLAN VENDIDO | J2: FECHA ALTA | K2: DÍAS DESDE CONTACTO | L2: CUIL | M2: OS ACTUAL | N2: PLAN ACTUAL | O2: DELEGACIÓN | P2: OBSERVACIONES
A3: 46223 | B3: =IF(A3="","",TEXT(A3,"MM-YYYY")) -> 07-2026 | C3: Micaela | D3: 3517698641 | E3: TERRENO | F3: Sol | G3: CÓRDOBA | H3: En Contacto | K3: =IF(A3="","",TODAY()-A3) -> 17 | P3: esperando rta
A4: 46223 | B4: =IF(A4="","",TEXT(A4,"MM-YYYY")) -> 07-2026 | C4: Victoria | D4: 3518634762 | E4: TERRENO | F4: Sol | G4: CÓRDOBA | H4: Descartado | K4: =IF(A4="","",TODAY()-A4) -> 17 | P4: No Interesa por Costos / APROSS
A5: 46223 | B5: =IF(A5="","",TEXT(A5,"MM-YYYY")) -> 07-2026 | C5: Cristian | D5: 3813695292 | E5: TERRENO | F5: Sol | G5: CÓRDOBA | H5: En Contacto | K5: =IF(A5="","",TODAY()-A5) -> 17 | P5: esperando rta
A6: 46223 | B6: =IF(A6="","",TEXT(A6,"MM-YYYY")) -> 07-2026 | D6: 3512009357 | E6: TERRENO | F6: Sol | G6: CÓRDOBA | H6: En Contacto | K6: =IF(A6="","",TODAY()-A6) -> 17 | P6: esperando rta
A7: 46223 | B7: =IF(A7="","",TEXT(A7,"MM-YYYY")) -> 07-2026 | D7: 3576447836 | E7: TERRENO | F7: Sol | G7: CÓRDOBA | H7: En Contacto | K7: =IF(A7="","",TODAY()-A7) -> 17 | P7: esperando rta
A8: 46223 | B8: =IF(A8="","",TEXT(A8,"MM-YYYY")) -> 07-2026 | D8: 3472584500 | E8: TERRENO | F8: Sol | G8: CÓRDOBA | H8: En Contacto | K8: =IF(A8="","",TODAY()-A8) -> 17 | P8: esperando rta
A9: 46223 | B9: =IF(A9="","",TEXT(A9,"MM-YYYY")) -> 07-2026 | C9: Supervisora | D9: 3512099449 | E9: TERRENO | F9: Sol | G9: CÓRDOBA | H9: Cotizado | K9: =IF(A9="","",TODAY()-A9) -> 17 | P9: Analizando
A10: 46223 | B10: =IF(A10="","",TEXT(A10,"MM-YYYY")) -> 07-2026 | C10: Tamara (referido) | D10: 3515 95-6465 | E10: TERRENO | F10: Sol | G10: CÓRDOBA | H10: Cotizado | K10: =IF(A10="","",TODAY()-A10) -> 17 | P10: Analizando
A11: 46225 | B11: =IF(A11="","",TEXT(A11,"MM-YYYY")) -> 07-2026 | C11: Luis | D11: 3513877479 | E11: TERRENO | F11: Sol | G11: CÓRDOBA | H11: Descartado | K11: =IF(A11="","",TODAY()-A11) -> 15 | P11: Preexistencia / OSPEVIC
A12: 46225 | B12: =IF(A12="","",TEXT(A12,"MM-YYYY")) -> 07-2026 | C12: Luis | D12: 3516157182 | E12: TERRENO | F12: Sol | G12: CÓRDOBA | H12: Cotizado | K12: =IF(A12="","",TODAY()-A12) -> 15 | P12: Analizando
A13: 46225 | B13: =IF(A13="","",TEXT(A13,"MM-YYYY")) -> 07-2026 | C13: Santi | D13: 3512547404 | E13: TERRENO | F13: Sol | G13: CÓRDOBA | H13: En Contacto | K13: =IF(A13="","",TODAY()-A13) -> 15 | P13: esperando rta
A14: 46225 | B14: =IF(A14="","",TEXT(A14,"MM-YYYY")) -> 07-2026 | C14: Hernan | D14: 3512510005 | E14: TERRENO | F14: Sol | G14: CÓRDOBA | H14: En Contacto | K14: =IF(A14="","",TODAY()-A14) -> 15 | P14: esperando rta
A15: 46226 | B15: =IF(A15="","",TEXT(A15,"MM-YYYY")) -> 07-2026 | C15: Fabri | D15: 3512145612 | E15: TERRENO | F15: Sol | G15: CÓRDOBA | H15: En Contacto | K15: =IF(A15="","",TODAY()-A15) -> 14 | P15: esperando rta / SIPSSA
A16: 46226 | B16: =IF(A16="","",TEXT(A16,"MM-YYYY")) -> 07-2026 | C16: Lucio | D16: 3513445175 | E16: TERRENO | F16: Sol | G16: CÓRDOBA | H16: En Contacto | K16: =IF(A16="","",TODAY()-A16) -> 14 | P16: esperando rta / SIPSSA
A17: 46226 | B17: =IF(A17="","",TEXT(A17,"MM-YYYY")) -> 07-2026 | C17: Maycol | D17: 3516345768 | E17: TERRENO | F17: Sol | G17: CÓRDOBA | H17: En Contacto | K17: =IF(A17="","",TODAY()-A17) -> 14 | P17: esperando rta
A18: 46226 | B18: =IF(A18="","",TEXT(A18,"MM-YYYY")) -> 07-2026 | C18: Ivan | D18: 3513837639 | E18: TERRENO | F18: Sol | G18: CÓRDOBA | H18: En Contacto | K18: =IF(A18="","",TODAY()-A18) -> 14 | P18: esperando rta
A19: 46226 | B19: =IF(A19="","",TEXT(A19,"MM-YYYY")) -> 07-2026 | C19: Javier | D19: 3513933807 | E19: TERRENO | F19: Sol | G19: CÓRDOBA | H19: En Contacto | K19: =IF(A19="","",TODAY()-A19) -> 14 | P19: esperando rta
A20: 46226 | B20: =IF(A20="","",TEXT(A20,"MM-YYYY")) -> 07-2026 | C20: Alexis | D20: 3516426155 | E20: TERRENO | F20: Sol | G20: CÓRDOBA | H20: En Contacto | K20: =IF(A20="","",TODAY()-A20) -> 14 | P20: esperando rta
... A45: 46232 | B45: =IF(A45="","",TEXT(A45,"MM-YYYY")) -> 07-2026 | C45: Eric | D45: 3572587668 | E45: TERRENO | F45: Sol | G45: RIO SEGUNDO | H45: En Contacto | K45: =IF(A45="","",TODAY()-A45) -> 8 | P45: esperando rta / OBRA SOCIAL DE LA FÁBRICA - APORTES
A46: 46233 | B46: =IF(A46="","",TEXT(A46,"MM-YYYY")) -> 07-2026 | C46: Brisa | D46: 3547654286 | E46: TERRENO | F46: Sol | H46: Lead | K46: =IF(A46="","",TODAY()-A46) -> 7
A47: 46233 | B47: =IF(A47="","",TEXT(A47,"MM-YYYY")) -> 07-2026 | C47: Bruno | D47: 3547608135 | E47: TERRENO | F47: Sol | H47: Lead | K47: =IF(A47="","",TODAY()-A47) -> 7 | P47: Hector (papá) / APORTE: 17780817
A48: 46233 | B48: =IF(A48="","",TEXT(A48,"MM-YYYY")) -> 07-2026 | C48: Rocio | D48: 3547656197 | E48: TERRENO | F48: Sol | H48: Lead | K48: =IF(A48="","",TODAY()-A48) -> 7
A49: 46234 | B49: =IF(A49="","",TEXT(A49,"MM-YYYY")) -> 07-2026 | C49: Leonardo | D49: 3572609169 | E49: TERRENO | F49: Sol | H49: Lead | K49: =IF(A49="","",TODAY()-A49) -> 6 | P49: Fábrica: LOGROS (Periodo)
A50: 46234 | B50: =IF(A50="","",TEXT(A50,"MM-YYYY")) -> 07-2026 | C50: Angel | D50: 3572606463 | E50: TERRENO | F50: Sol | H50: Lead | K50: =IF(A50="","",TODAY()-A50) -> 6 | P50: OBRA SOCIAL - Fábrica
A51: 46234 | B51: =IF(A51="","",TEXT(A51,"MM-YYYY")) -> 07-2026 | C51: Daniel | D51: 3572447843 | E51: TERRENO | F51: Sol | H51: Lead | K51: =IF(A51="","",TODAY()-A51) -> 6
A52: 46223 | B52: =IF(A52="","",TEXT(A52,"MM-YYYY")) -> 07-2026 | C52: 3515585305 | D52: Javier chaparro | E52: TERRENO | F52: Juli | H52: Descartado | K52: =IF(A52="","",TODAY()-A52) -> 17 | P52: No puede Desregular / Base Miercoles
A53: 46223 | B53: =IF(A53="","",TEXT(A53,"MM-YYYY")) -> 07-2026 | C53: 3515133675 | D53: Matias Mariño | E53: TERRENO | F53: Juli | H53: Descartado | K53: =IF(A53="","",TODAY()-A53) -> 17 | P53: No puede Desregular / Zona miercoles
A54: 46223 | B54: =IF(A54="","",TEXT(A54,"MM-YYYY")) -> 07-2026 | C54: 3513223740 | D54: Miguel Sanchez | E54: TERRENO | F54: Juli | H54: Descartado | K54: =IF(A54="","",TODAY()-A54) -> 17 | P54: quiere permanecer en gea por costos y por el Sanotorio Allende / Zona miercoles
A55: 46223 | B55: =IF(A55="","",TEXT(A55,"MM-YYYY")) -> 07-2026 | C55: 3576477300 | D55: Tomas Rio | E55: TERRENO | F55: Juli | H55: En Contacto | K55: =IF(A55="","",TODAY()-A55) -> 17 | P55: llame y mande msjs y no respondio nunca / Zona miercoles
A56: 46225 | B56: =IF(A56="","",TEXT(A56,"MM-YYYY")) -> 07-2026 | C56: 3512465207 | D56: Paolo Albertini | E56: TERRENO | F56: Juli | H56: Cotizado | K56: =IF(A56="","",TODAY()-A56) -> 15 | P56: Analizando / Zona miercoles
A57: 46226 | B57: =IF(A57="","",TEXT(A57,"MM-YYYY")) -> 07-2026 | C57: 3518107536 | D57: Monica Carrizo | E57: TERRENO | F57: Juli | H57: En Contacto | K57: =IF(A57="","",TODAY()-A57) -> 14 | P57: No responde llamada ni Mensajes / Porta jueves
A58: 46226 | B58: =IF(A58="","",TEXT(A58,"MM-YYYY")) -> 07-2026 | C58: 3512839355 | D58: Ricardo Santa Cuz | E58: TERRENO | F58: Juli | H58: Cotizado | K58: =IF(A58="","",TODAY()-A58) -> 14 | P58: Analizando / Urea Automotor
A59: 46226 | B59: =IF(A59="","",TEXT(A59,"MM-YYYY")) -> 07-2026 | C59: 3517558689 | D59: Rodrigo Abdala | E59: TERRENO | F59: Juli | H59: Descartado | K59: =IF(A59="","",TODAY()-A59) -> 14 | P59: No puede Desregular / Urea Automotor
A60: 46226 | B60: =IF(A60="","",TEXT(A60,"MM-YYYY")) -> 07-2026 | C60: 3513839599 | D60: Maximiliano Varela | E60: TERRENO | F60: Juli | H60: Descartado | K60: =IF(A60="","",TODAY()-A60) -> 14 | P60: Premedic/ No puede Desregular / ITV
A61: 46226 | B61: =IF(A61="","",TEXT(A61,"MM-YYYY")) -> 07-2026 | C61: 3515949702 | D61: Arce Nicolas | E61: TERRENO | F61: Juli | H61: En Contacto | K61: =IF(A61="","",TODAY()-A61) -> 14 | P61: llame varias veces y no respondio ni llamadasni msj / ITV
A62: 46226 | B62: =IF(A62="","",TEXT(A62,"MM-YYYY")) -> 07-2026 | C62: 3515435436 | D62: Esteban Avila | E62: TERRENO | F62: Juli | H62: Descartado | K62: =IF(A62="","",TODAY()-A62) -> 14 | P62: quiere permanecer en gea por costos y por el Sanotorio Allende / Cauplas
A63: 46226 | B63: =IF(A63="","",TEXT(A63,"MM-YYYY")) -> 07-2026 | C63: 3513998072 | D63: Pablo Castillo | E63: TERRENO | F63: Juli | H63: Descartado | K63: =IF(A63="","",TODAY()-A63) -> 14 | P63: quiere permanecer en su O.S por costos / Vidrios
... A66: 46227 | B66: =IF(A66="","",TEXT(A66,"MM-YYYY")) -> 07-2026 | C66: 3518128055 | D66: Alejandro Zarraja | E66: TERRENO | F66: Juli | H66: En Contacto | K66: =IF(A66="","",TODAY()-A66) -> 13 | P66: No responde llamada ni Mensajes / plaza
B67: =IF(A67="","",TEXT(A67,"MM-YYYY")) | D67: INTERIOR | E67: TERRENO | F67: Juli | H67: Lead | K67: =IF(A67="","",TODAY()-A67)
A68: 46230 | B68: =IF(A68="","",TEXT(A68,"MM-YYYY")) -> 07-2026 | C68: 3572607383 | D68: Facundo Alvarez | E68: TERRENO | F68: Juli | H68: Descartado | K68: =IF(A68="","",TODAY()-A68) -> 10 | P68: No puede pagar / pilar estacion srv
A69: 46230 | B69: =IF(A69="","",TEXT(A69,"MM-YYYY")) -> 07-2026 | C69: 3572524324 | D69: Diego Fernandez | E69: TERRENO | F69: Juli | H69: Cotizado | K69: =IF(A69="","",TODAY()-A69) -> 10 | P69: Analizando / Pilar Diatribuidor
A70: 46230 | B70: =IF(A70="","",TEXT(A70,"MM-YYYY")) -> 07-2026 | C70: 3572673287 | D70: Yanina Cabrera | E70: TERRENO | F70: Juli | H70: Descartado | K70: =IF(A70="","",TODAY()-A70) -> 10 | P70: Embarazada / Pilar Polleria
A71: 46230 | B71: =IF(A71="","",TEXT(A71,"MM-YYYY")) -> 07-2026 | C71: 3572671852 | D71: Gabriela Rodriguez | E71: TERRENO | F71: Juli | H71: Cotizado | K71: =IF(A71="","",TODAY()-A71) -> 10 | P71: lo charla con la pareja / Pilar Forrajeria
A72: 46230 | B72: =IF(A72="","",TEXT(A72,"MM-YYYY")) -> 07-2026 | C72: 3572448529 | D72: Ferreteria | E72: TERRENO | F72: Juli | H72: Descartado | K72: =IF(A72="","",TODAY()-A72) -> 10 | P72: ir a visitar a la esposa ya tienen toda la info - No puede desregurar / Pilar ferreteria
A73: 46230 | B73: =IF(A73="","",TEXT(A73,"MM-YYYY")) -> 07-2026 | C73: 3572530834 | D73: Cuello Johana | E73: TERRENO | F73: Juli | H73: Cotizado | K73: =IF(A73="","",TODAY()-A73) -> 10 | P73: Analizando / Pilar
A74: 46230 | B74: =IF(A74="","",TEXT(A74,"MM-YYYY")) -> 07-2026 | C74: 3572522288 | D74: Gaston Gauna | E74: TERRENO | F74: Juli | H74: Cotizado | K74: =IF(A74="","",TODAY()-A74) -> 10 | P74: Esperando recibo para cotizar / Rio2 Logro Fri,
A75: 46230 | B75: =IF(A75="","",TEXT(A75,"MM-YYYY")) -> 07-2026 | C75: 3572444732 | D75: Mauro | E75: TERRENO | F75: Juli | H75: Cotizado | K75: =IF(A75="","",TODAY()-A75) -> 10 | P75: Analizando / Rio2 Logro Fri,
A76: 46230 | B76: =IF(A76="","",TEXT(A76,"MM-YYYY")) -> 07-2026 | C76: 3572570691 | D76: Rojas Gustavo | E76: TERRENO | F76: Juli | H76: Cotizado | K76: =IF(A76="","",TODAY()-A76) -> 10 | P76: Analizando / Rio2 Logro Fri,
A77: 46233 | B77: =IF(A77="","",TEXT(A77,"MM-YYYY")) -> 07-2026 | C77: 3518023412 | D77: Brenda Estella | E77: TERRENO | F77: Juli | H77: Cotizado | K77: =IF(A77="","",TODAY()-A77) -> 7 | P77: Analizando / Alta Gracia
A78: 46233 | B78: =IF(A78="","",TEXT(A78,"MM-YYYY")) -> 07-2026 | C78: 3547662572 | D78: Melisa Saucedo | E78: TERRENO | F78: Juli | H78: Cotizado | K78: =IF(A78="","",TODAY()-A78) -> 7 | P78: Analizando / Alta Gracia
A79: 46233 | B79: =IF(A79="","",TEXT(A79,"MM-YYYY")) -> 07-2026 | C79: 3517638802 | D79: Neister lopez | E79: TERRENO | F79: Juli | H79: Cotizado | K79: =IF(A79="","",TODAY()-A79) -> 7 | P79: Analizando- Prob económicos / Alta Gracia
... A81: 46234 | B81: =IF(A81="","",TEXT(A81,"MM-YYYY")) -> 07-2026 | C81: 3572684885 | D81: Lautaro | E81: TERRENO | F81: Juli | H81: Cotizado | K81: =IF(A81="","",TODAY()-A81) -> 6 | P81: Analizando / Rio2 Logro Fri,
A82: 46226 | B82: =IF(A82="","",TEXT(A82,"MM-YYYY")) -> 07-2026 | C82: ulises | D82: 35135355461 | E82: TERRENO | F82: Vane | H82: Cotizado | K82: =IF(A82="","",TODAY()-A82) -> 14 | P82: Analizando / sindicato
A83: 46226 | B83: =IF(A83="","",TEXT(A83,"MM-YYYY")) -> 07-2026 | C83: gaston | D83: 3516642188 | E83: TERRENO | F83: Vane | H83: Descartado | K83: =IF(A83="","",TODAY()-A83) -> 14 | P83: No Interesa por Costos / no llegan los mensajes
A84: 46226 | B84: =IF(A84="","",TEXT(A84,"MM-YYYY")) -> 07-2026 | C84: ruben | D84: 3515640864 | E84: TERRENO | F84: Vane | H84: Descartado | K84: =IF(A84="","",TODAY()-A84) -> 14 | P84: No Interesa por Costos / no tiene
A85: 46226 | B85: =IF(A85="","",TEXT(A85,"MM-YYYY")) -> 07-2026 | C85: nahuel | D85: 3513525911 | E85: TERRENO | F85: Vane | H85: Descartado | K85: =IF(A85="","",TODAY()-A85) -> 14 | P85: No Interesa por Costos / no contesta
A86: 46226 | B86: =IF(A86="","",TEXT(A86,"MM-YYYY")) -> 07-2026 | C86: catriel | D86: 3517686440 | E86: TERRENO | F86: Vane | H86: Descartado | K86: =IF(A86="","",TODAY()-A86) -> 14 | P86: No Interesa por Costos / vidrio
A87: 46226 | B87: =IF(A87="","",TEXT(A87,"MM-YYYY")) -> 07-2026 | C87: dario | D87: 3512694664 | E87: TERRENO | F87: Vane | H87: Descartado | K87: =IF(A87="","",TODAY()-A87) -> 14 | P87: No Interesa por Costos, el paga 12,000 extras de su sueldo / vidrio
A88: 46230 | B88: =IF(A88="","",TEXT(A88,"MM-YYYY")) -> 07-2026 | C88: sol | D88: 358671851 | E88: TERRENO | F88: Vane | H88: En Contacto | K88: =IF(A88="","",TODAY()-A88) -> 10 | P88: sin respuesta / terreno
A89: 46230 | B89: =IF(A89="","",TEXT(A89,"MM-YYYY")) -> 07-2026 | C89: pricila | D89: 3517917433 | E89: TERRENO | F89: Vane | H89: En Contacto | K89: =IF(A89="","",TODAY()-A89) -> 10 | P89: sin respuesta / terrerno
A90: 46230 | B90: =IF(A90="","",TEXT(A90,"MM-YYYY")) -> 07-2026 | C90: maidana vanesa | D90: 3513211896 | E90: TERRENO | F90: Vane | H90: En Contacto | K90: =IF(A90="","",TODAY()-A90) -> 10 | P90: nunca contesto / terreno
A91: 46230 | B91: =IF(A91="","",TEXT(A91,"MM-YYYY")) -> 07-2026 | C91: joaquin carballo | D91: 3519016723 | E91: TERRENO | F91: Vane | H91: Descartado | K91: =IF(A91="","",TODAY()-A91) -> 10 | P91: No Interesa por Costos / no quiere pagar diferencia / terreno
B92: =IF(A92="","",TEXT(A92,"MM-YYYY")) | C92: yonatan Dias | D92: 35113175522 | E92: TERRENO | F92: Vane | H92: Descartado | K92: =IF(A92="","",TODAY()-A92) | P92: No Interesa por Costos / terreno
A93: 46230 | B93: =IF(A93="","",TEXT(A93,"MM-YYYY")) -> 07-2026 | C93: Valentina albarracin | D93: 3513662971 | E93: TERRENO | F93: Vane | H93: En Contacto | K93: =IF(A93="","",TODAY()-A93) -> 10 | P93: no contesto / terreno
A94: 46230 | B94: =IF(A94="","",TEXT(A94,"MM-YYYY")) -> 07-2026 | C94: cred | D94: 3512295832 | E94: TERRENO | F94: Vane | H94: En Contacto | K94: =IF(A94="","",TODAY()-A94) -> 10 | P94: no contesto / terreno
A95: 46231 | B95: =IF(A95="","",TEXT(A95,"MM-YYYY")) -> 07-2026 | C95: pablo leonardo | D95: 3572682566 | E95: TERRENO | F95: Vane | H95: Descartado | K95: =IF(A95="","",TODAY()-A95) -> 9 | P95: No puede Desregular / pilar
A96: 46231 | B96: =IF(A96="","",TEXT(A96,"MM-YYYY")) -> 07-2026 | C96: marcos vallozzi | D96: 3572594952 | E96: TERRENO | F96: Vane | H96: Descartado | K96: =IF(A96="","",TODAY()-A96) -> 9 | P96: No Interesa por Costos / no quiere pagar diferencia / osde
A97: 46231 | B97: =IF(A97="","",TEXT(A97,"MM-YYYY")) -> 07-2026 | C97: Alicia Albert | D97: 3572581200 | E97: TERRENO | F97: Vane | H97: Cotizado | K97: =IF(A97="","",TODAY()-A97) -> 9 | P97: Cotizado Sin respuesta Posterior / s-c
A98: 46231 | B98: =IF(A98="","",TEXT(A98,"MM-YYYY")) -> 07-2026 | C98: carlos gonzales | D98: 3572609322 | E98: TERRENO | F98: Vane | H98: Descartado | K98: =IF(A98="","",TODAY()-A98) -> 9 | P98: Preexistencia / VEGA
A99: 46231 | B99: =IF(A99="","",TEXT(A99,"MM-YYYY")) -> 07-2026 | C99: mauricio oliva | D99: 3572504755 | E99: TERRENO | F99: Vane | H99: Descartado | K99: =IF(A99="","",TODAY()-A99) -> 9 | P99: no quiere cambiarce por el momento / MET
A100: 46231 | B100: =IF(A100="","",TEXT(A100,"MM-YYYY")) -> 07-2026 | C100: roberto zamora | D100: 3572605341 | E100: TERRENO | F100: Vane | H100: Descartado | K100: =IF(A100="","",TODAY()-A100) -> 9 | P100: Quiere el Allende / Somos mas caros / GEA
A101: 46231 | B101: =IF(A101="","",TEXT(A101,"MM-YYYY")) -> 07-2026 | C101: aAlexis | D101: 3572606512 | E101: TERRENO | F101: Vane | H101: En Contacto | K101: =IF(A101="","",TODAY()-A101) -> 9 | P101: No responde Mensajes ni Llamadas
A102: 46231 | B102: =IF(A102="","",TEXT(A102,"MM-YYYY")) -> 07-2026 | C102: cuello brian | D102: 3572539307 | E102: TERRENO | F102: Vane | H102: Descartado | K102: =IF(A102="","",TODAY()-A102) -> 9 | P102: no le interesa por el momento / NOBIS
A103: 46231 | B103: =IF(A103="","",TEXT(A103,"MM-YYYY")) -> 07-2026 | C103: Gabriel | D103: 3572617054 | E103: TERRENO | F103: Vane | H103: Cotizado | K103: =IF(A103="","",TODAY()-A103) -> 9 | P103: Analizando / SERVIRED
A104: 46231 | B104: =IF(A104="","",TEXT(A104,"MM-YYYY")) -> 07-2026 | C104: Jonas | D104: 3572550326 | E104: TERRENO | F104: Vane | H104: Cotizado | K104: =IF(A104="","",TODAY()-A104) -> 9 | P104: Analizando / NOBIS
... A117: 46238 | B117: =IF(A117="","",TEXT(A117,"MM-YYYY")) -> 08-2026 | C117: ALDI | D117: 3515529104 | E117: TERRENO | F117: Vane | H117: En Contacto | K117: =IF(A117="","",TODAY()-A117) -> 2 | P117: No responde Mensajes ni Llamadas / -
B118: =IF(A118="","",TEXT(A118,"MM-YYYY")) | C118: SUAREZ, NICOLAS EDUARDO | D118: 3385434722 | E118: OSPIF | F118: Juli | G118: LABOULAYE | H118: En Contacto | K118: =IF(A118="","",TODAY()-A118) | L118: 20371932446 | M118: Grupo Azul-CBA. | N118: PLAN BASICO | O118: OSPIF ALTA GRACIA | P118: esperando respuesta / Contactado 3 veces
B119: =IF(A119="","",TEXT(A119,"MM-YYYY")) | C119: GIMENEZ, HECTOR EMANUEL | D119: 49023032 | E119: OSPIF | F119: Juli | G119: COLAZO | H119: En Contacto | K119: =IF(A119="","",TODAY()-A119) | L119: 20366841742 | M119: Grupo Azul-CBA. | N119: PLAN BASICO | O119: OSPIF ALTA GRACIA | P119: Sin Servicio
B120: =IF(A120="","",TEXT(A120,"MM-YYYY")) | C120: AHUMADA, YANINA DANIELA | D120: 03532-412672 | E120: OSPIF | F120: Juli | G120: OLIVA | H120: En Contacto | K120: =IF(A120="","",TODAY()-A120) | L120: 27354718702 | M120: Grupo Azul-CBA. | N120: PLAN BASICO | O120: OSPIF ALTA GRACIA | P120: Sin Servicio
B121: =IF(A121="","",TEXT(A121,"MM-YYYY")) | C121: TISERA, HUGO | D121: 151111111 | E121: OSPIF | F121: Juli | G121: TANCACHA | H121: En Contacto | K121: =IF(A121="","",TODAY()-A121) | L121: 20366030426 | M121: Grupo Azul-CBA. | N121: PLAN BASICO | O121: OSPIF ALTA GRACIA | P121: Sin Servicio
B122: =IF(A122="","",TEXT(A122,"MM-YYYY")) | C122: MATELLICA, EMILIANO | D122: 49037599 | E122: OSPIF | F122: Juli | G122: OLIVA | H122: En Contacto | K122: =IF(A122="","",TODAY()-A122) | L122: 20361308884 | M122: Grupo Azul-CBA. | N122: PLAN BASICO | O122: OSPIF ALTA GRACIA | P122: Sin Servicio
B123: =IF(A123="","",TEXT(A123,"MM-YYYY")) | C123: CARDOZO, JUAN RAMON | D123: 0353-4254271 | E123: OSPIF | F123: Juli | G123: CARRILOBO | H123: En Contacto | K123: =IF(A123="","",TODAY()-A123) | L123: 20370643173 | M123: Grupo Azul-CBA. | N123: PLAN BASICO | O123: OSPIF ALTA GRACIA | P123: Sin Servicio
B124: =IF(A124="","",TEXT(A124,"MM-YYYY")) | C124: MOYANO, CLAUDIO LUCAS | D124: 3525576380 | E124: OSPIF | F124: Juli | G124: BUENA VISTA, DEPARTAMENTO SANT | H124: En Contacto | K124: =IF(A124="","",TODAY()-A124) | L124: 20356769830 | M124: Grupo Azul-CBA. | N124: PLAN BASICO | O124: OSPIF ALTA GRACIA | P124: Numero Inexistente
B125: =IF(A125="","",TEXT(A125,"MM-YYYY")) | C125: CIANI, FATIMA BELEN | E125: OSPIF | F125: Juli | G125: SAN SEVERO | H125: En Contacto | K125: =IF(A125="","",TODAY()-A125) | L125: 27367150373 | M125: Grupo Azul-CBA. | N125: PLAN BASICO | O125: OSPIF ALTA GRACIA | P125: Sin Servicio
B126: =IF(A126="","",TEXT(A126,"MM-YYYY")) | C126: BENITEZ, FERNANDO JULIAN | D126: 3468416311 | E126: OSPIF | F126: Juli | G126: LA CESIRA | H126: En Contacto | K126: =IF(A126="","",TODAY()-A126) | L126: 20363669566 | M126: Grupo Azul-CBA. | N126: PLAN BASICO | O126: OSPIF ALTA GRACIA | P126: Sin Servicio
B127: =IF(A127="","",TEXT(A127,"MM-YYYY")) | C127: SAVATERO, MARTIN LEONARDO | D127: 3576657112 | E127: OSPIF | F127: Juli | G127: ARROYITO | H127: En Contacto | K127: =IF(A127="","",TODAY()-A127) | L127: 20356553978 | M127: O.S.P.I.F. | N127: PLAN BASICO RG | O127: OSPIF CORDOBA | P127: esperando respuesta / Contactado 3 veces
B128: =IF(A128="","",TEXT(A128,"MM-YYYY")) | C128: AMAYA, ELIZABET JANET | D128: 3585609186 | E128: OSPIF | F128: Juli | G128: ALEJANDRO ROCA | H128: En Contacto | K128: =IF(A128="","",TODAY()-A128) | L128: 27365873432 | M128: Grupo Azul-CBA. | N128: PLAN UNICO | O128: OSPIF ALTA GRACIA | P128: Sin Servicio
B129: =IF(A129="","",TEXT(A129,"MM-YYYY")) | C129: GOMEZ, MARCELO RAMON | D129: 3573444808 | E129: OSPIF | F129: Juli | G129: VILLA DEL ROSARIO | H129: En Contacto | K129: =IF(A129="","",TODAY()-A129) | L129: 20346856662 | M129: Grupo Azul-CBA. | N129: PLAN BASICO | O129: OSPIF ALTA GRACIA | P129: esperando respuesta / Contactado 3 veces
B130: =IF(A130="","",TEXT(A130,"MM-YYYY")) | C130: LIMA, EMANUEL VALENTIN | D130: 3468515239 | E130: OSPIF | F130: Juli | G130: ISLA VERDE, DEPARTAMENTO MARCO | H130: En Contacto | K130: =IF(A130="","",TODAY()-A130) | L130: 23348184849 | M130: Grupo Azul-CBA. | N130: PLAN BASICO | O130: OSPIF ALTA GRACIA | P130: esperando respuesta / Contactado 3 veces
B131: =IF(A131="","",TEXT(A131,"MM-YYYY")) | C131: ALEMANY, MARIA FLORENCIA | D131: 351 6064604 | E131: OSPIF | F131: Juli | G131: Ciudad CÓRDOBA (CENTRO) | H131: En Contacto | K131: =IF(A131="","",TODAY()-A131) | L131: 27352839693 | M131: O.S.P.I.F. | N131: PLAN BASICO GEN | O131: OSPIF CORDOBA | P131: esperando respuesta / Contactado 3 veces
B132: =IF(A132="","",TEXT(A132,"MM-YYYY")) | C132: RAPOSO, LEILA FERNANDA | D132: 3467-446073 | E132: OSPIF | F132: Juli | G132: MONTE BUEY | H132: En Contacto | K132: =IF(A132="","",TODAY()-A132) | L132: 27351299385 | M132: Grupo Azul-CBA. | N132: PLAN BASICO | O132: OSPIF ALTA GRACIA | P132: Sin Servicio
B133: =IF(A133="","",TEXT(A133,"MM-YYYY")) | C133: FISSORE, MARIA CELESTE | D133: 49037599 | E133: OSPIF | F133: Juli | G133: SAN MARCOS SUD | H133: En Contacto | K133: =IF(A133="","",TODAY()-A133) | L133: 27340519839 | M133: Grupo Azul-CBA. | N133: PLAN BASICO | O133: OSPIF ALTA GRACIA | P133: Sin Servicio
B134: =IF(A134="","",TEXT(A134,"MM-YYYY")) | C134: RIVERO, RENE RAFAEL | D134: 3535198354 | E134: OSPIF | F134: Juli | G134: COLAZO | H134: Descartado | K134: =IF(A134="","",TODAY()-A134) | L134: 20350948105 | M134: O.S.P.I.F. | N134: PLAN BASICO RG | O134: OSPIF CORDOBA | P134: Prexistencia
B135: =IF(A135="","",TEXT(A135,"MM-YYYY")) | C135: GAUNA, NOELIA FABIANA | D135: 3512111099 | E135: OSPIF | F135: Juli | G135: CORDOBA | H135: En Contacto | K135: =IF(A135="","",TODAY()-A135) | L135: 24348842907 | M135: O.S.P.I.F. | N135: PLAN BASICO GEN | O135: OSPIF CORDOBA | P135: esperando respuesta / Contactado 3 veces
B136: =IF(A136="","",TEXT(A136,"MM-YYYY")) | C136: LEDESMA, PABLO JEREMIAS | D136: 3515942308 | E136: OSPIF | F136: Juli | G136: BARRIO SAN VICENTE | H136: En Contacto | K136: =IF(A136="","",TODAY()-A136) | L136: 20355255981 | M136: O.S.P.I.F. | N136: PLAN BASICO GEN | O136: OSPIF CORDOBA | P136: esperando respuesta / Contactado 3 veces
B137: =IF(A137="","",TEXT(A137,"MM-YYYY")) | C137: PEREYRA, MAYCO ROMAN | D137: 03532-421655 | E137: OSPIF | F137: Juli | G137: OLIVA | H137: En Contacto | K137: =IF(A137="","",TODAY()-A137) | L137: 20338814462 | M137: Grupo Azul-CBA. | N137: PLAN BASICO | O137: OSPIF ALTA GRACIA | P137: Fuera de servicio
... B245: =IF(A245="","",TEXT(A245,"MM-YYYY")) | C245: CID, JOSEFA DEL PILAR | D245: 03573-431973 | E245: OSPIF | F245: Vane | G245: VILLA DEL ROSARIO | H245: En Contacto | K245: =IF(A245="","",TODAY()-A245) | L245: 27295625835 | M245: Grupo Azul-CBA. | N245: PLAN BASICO | O245: OSPIF ALTA GRACIA | P245: Sin Linea
B246: =IF(A246="","",TEXT(A246,"MM-YYYY")) | C246: BARRAZA, JORGE GASTON | D246: 03385-15402298 | E246: OSPIF | F246: Vane | G246: LABOULAYE | H246: Cerrado | I246: GS200 | K246: =IF(A246="","",TODAY()-A246) | L246: 20290006938 | M246: Grupo Azul-CBA. | N246: PLAN BASICO | O246: OSPIF ALTA GRACIA | P246: GS200
...

Sheet RESUMEN
A1: RESUMEN COMERCIAL
A3: POR ESTADO | D3: POR COMERCIAL
A4: Lead | B4: =COUNTIF(BBDD!H:H,"Lead") -> 8 | D4: Sol | E4: =COUNTIF(BBDD!F:F,"Sol") -> 49
A5: En Contacto | B5: =COUNTIF(BBDD!H:H,"En Contacto") -> 220 | D5: Vane | E5: =COUNTIF(BBDD!F:F,"Vane") -> 133
A6: Cotizado | B6: =COUNTIF(BBDD!H:H,"Cotizado") -> 30 | D6: Juli | E6: =COUNTIF(BBDD!F:F,"Juli") -> 128
A7: Cerrado | B7: =COUNTIF(BBDD!H:H,"Cerrado") -> 3
A8: Descartado | B8: =COUNTIF(BBDD!H:H,"Descartado") -> 49
A10: VENTAS GS200 | B10: =COUNTIF(BBDD!I:I,"GS200") -> 3
A11: VENTAS GS100 | B11: =COUNTIF(BBDD!I:I,"GS100") -> 0
A12: TOTAL LEADS | B12: =COUNTA(BBDD!C:C)-1 -> 306

Sheet LISTAS
A1: ESTADO | B1: CANAL | C1: COMERCIAL | D1: PLAN_VENDIDO
A2: Lead | B2: TERRENO | C2: Sol | D2: GS100
A3: En Contacto | B3: OSPIF | C3: Vane | D3: GS200
A4: Cotizado | C4: Juli
A5: Cerrado
A6: Descartado
